pycolarized/__init__.py
pycolarized/ansi.py
pycolarized/ansitowin32.py
pycolarized/initialise.py
pycolarized/win32.py
pycolarized/winterm.py
pycolarized/tests/__init__.py
pycolarized/tests/ansi_test.py
pycolarized/tests/ansitowin32_test.py
pycolarized/tests/initialise_test.py
pycolarized/tests/isatty_test.py
pycolarized/tests/utils.py
pycolarized/tests/winterm_test.py
pycolarized-2.2.5.dist-info/LICENSE.txt
pycolarized-2.2.5.dist-info/METADATA
pycolarized-2.2.5.dist-info/WHEEL
pycolarized-2.2.5.dist-info/top_level.txt
pycolarized-2.2.5.dist-info/RECORD
