Metadata-Version: 2.1
Name: pycolarized
Version: 2.2.5
Summary: python package to style terminal
Home-page: https://github.com
Author: smithjack
Author-email: smithey120@gmail.com
Classifier: Programming Language :: Python :: 3
Classifier: License :: OSI Approved :: MIT License
Classifier: Operating System :: OS Independent
Requires-Python: >=3.7
License-File: LICENSE.txt
